{"night": {"3": 545, "1": 8310, "2": 1450, "12": 28, "4": 181, "6": 100, "8": 45, "5": 117, "11": 22, "7": 53, "9": 24, "10": 42}, "evening": {"4": 115, "1": 4029, "3": 254, "2": 873, "5": 75, "8": 106, "7": 96, "6": 80, "10": 84, "12": 14, "11": 42, "9": 61}, "morning": {"3": 139, "1": 1724, "7": 42, "8": 34, "5": 61, "2": 467, "9": 28, "12": 5, "4": 93, "6": 37, "10": 31, "11": 18}, "noon": {"1": 210, "2": 73, "9": 3, "3": 38, "7": 5, "8": 3, "12": 10, "4": 13, "5": 7, "11": 2, "10": 1, "6": 7}, "afternoon": {"4": 111, "1": 902, "3": 150, "2": 310, "5": 89, "6": 31, "11": 4, "8": 13, "10": 5, "7": 10, "12": 11, "9": 3}}