{"night": {"15": 545, "1": 8310, "14": 1450, "24": 28, "16": 181, "18": 100, "20": 45, "17": 117, "23": 22, "19": 53, "21": 24, "22": 42, "start": 14.0, "end": 1.0}, "evening": {"16": 115, "13": 4029, "15": 254, "14": 873, "17": 75, "20": 106, "19": 96, "18": 80, "10": 84, "24": 14, "11": 42, "9": 61, "start": 13.0, "end": 14.0}, "morning": {"3": 139, "1": 1724, "7": 42, "8": 34, "5": 61, "2": 467, "9": 28, "12": 5, "4": 93, "6": 37, "10": 31, "11": 18, "start": 1.0, "end": 2.0}, "noon": {"13": 210, "2": 73, "9": 3, "3": 38, "7": 5, "8": 3, "12": 10, "16": 13, "17": 7, "11": 2, "22": 1, "6": 7, "start": 2.0, "end": 3.0}, "afternoon": {"4": 111, "13": 902, "3": 150, "14": 310, "5": 89, "6": 31, "11": 4, "8": 13, "10": 5, "7": 10, "12": 11, "9": 3, "start": 3.0, "end": 13.0}}