{"night": {"6": 4951, "3": 7941, "5": 1073, "4": 1338, "1": 100786, "8": 619, "9": 1390, "2": 3819, "7": 1417, "10": 386, "11": 233, "12": 108}, "afternoon": {"1": 1998, "3": 226, "2": 108, "9": 53, "5": 95, "7": 87, "6": 115, "4": 83, "11": 18, "8": 34, "10": 15, "12": 3}, "morning": {"1": 1070, "5": 40, "6": 101, "8": 75, "11": 18, "3": 67, "10": 35, "7": 85, "9": 80, "2": 59, "12": 3, "4": 31}, "noon": {"1": 1469, "7": 14, "3": 106, "2": 104, "9": 14, "12": 22, "5": 6, "11": 1, "8": 4, "4": 22, "6": 25, "10": 5}, "evening": {"11": 2, "1": 481, "9": 38, "2": 24, "4": 7, "6": 16, "3": 35, "7": 37, "8": 48, "10": 5, "12": 2, "5": 13}}