{"morning": {"3": 134, "8": 55, "6": 53, "10": 88, "1": 335, "2": 87, "4": 190, "9": 43, "5": 69, "7": 58, "11": 3, "start": 1.0, "end": 10.0}, "afternoon": {"2": 56, "16": 44, "22": 26, "14": 30, "17": 20, "13": 65, "21": 3, "18": 9, "19": 10, "20": 5, "11": 1, "12": 1, "start": 12.0, "end": 13.0}, "evening": {"10": 139, "13": 428, "14": 163, "16": 67, "23": 6, "8": 33, "9": 46, "18": 38, "15": 159, "19": 72, "11": 14, "17": 45, "start": 13.0, "end": 14.0}, "night": {"15": 81, "1": 1616, "20": 37, "23": 6, "14": 259, "22": 355, "19": 128, "24": 6, "17": 79, "18": 61, "start": 14.0, "end": 1.0}, "noon": {"9": 10, "13": 149, "10": 72, "12": 3, "14": 25, "20": 7, "19": 6, "15": 47, "18": 6, "5": 8, "16": 16, "11": 2, "start": 10.0, "end": 12.0}}